autoregressive_diffusion_pytorch/__init__.py
autoregressive_diffusion_pytorch/autoregressive_diffusion.py
autoregressive_diffusion_pytorch/autoregressive_flow.py
autoregressive_diffusion_pytorch/image_trainer.py
autoregressive_diffusion_pytorch-0.3.0.dist-info/METADATA
autoregressive_diffusion_pytorch-0.3.0.dist-info/WHEEL
autoregressive_diffusion_pytorch-0.3.0.dist-info/licenses/LICENSE
autoregressive_diffusion_pytorch-0.3.0.dist-info/RECORD
