Metadata-Version: 2.4
Name: autoregressive-diffusion-pytorch
Version: 0.3.0
Summary: Autoregressive Diffusion - Pytorch
Project-URL: Homepage, https://pypi.org/project/autoregressive-diffusion-pytorch/
Project-URL: Repository, https://github.com/lucidrains/autoregressive-diffusion-pytorch
Author-email: Phil Wang <lucidrains@gmail.com>
License: MIT License
License-File: LICENSE
Keywords: artificial intelligence,deep learning,denoising diffusion,transformers
Classifier: Development Status :: 4 - Beta
Classifier: Intended Audience :: Developers
Classifier: License :: OSI Approved :: MIT License
Classifier: Programming Language :: Python :: 3.8
Classifier: Topic :: Scientific/Engineering :: Artificial Intelligence
Requires-Python: >=3.8
Requires-Dist: accelerate<=1.6.0
Requires-Dist: einops>=0.8.0
Requires-Dist: einx>=0.3.0
Requires-Dist: ema-pytorch
Requires-Dist: torch>=2.0
Requires-Dist: torchdiffeq
Requires-Dist: tqdm
Requires-Dist: x-transformers>=1.31.14
Provides-Extra: examples
Requires-Dist: numpy; extra == 'examples'
Requires-Dist: tqdm; extra == 'examples'
